README.rst
setup.cfg
setup.py
backtrack/__init__.py
backtrack/logger.py
backtrack.egg-info/PKG-INFO
backtrack.egg-info/SOURCES.txt
backtrack.egg-info/dependency_links.txt
backtrack.egg-info/top_level.txt